Workbook
Name Slicer_Category: #N/A
Name Slicer_Clean_Branch: #N/A
Name Slicer_Membership: #N/A

Sheet Pivot Analyse
A3: Row Labels | B3: Sum of Net_Sales | D3: Row Labels | E3: Sum of Net_Sales | G3: Row Labels | H3: Sum of Net_Sales | J3: Row Labels | K3: Sum of Net_Sales | M3: KPI | N3: Column1
A4: Dairy | B4: 40568.288 | D4: Aug | E4: 136636.57 | G4: UPI | H4: 60933.121 | J4: Cheese Slices | K4: 16201.041 | M4: Total Sales | N4: =SUM(Master_Data[Net_Sales]) -> 161291.92
A5: Beverages | B5: 36637.476 | D5: Sep | E5: 24655.351 | G5: CARD | H5: 59999.535 | J5: Cola 750ml | K5: 12841.132 | M5: Total Transactions | N5: =COUNTA(Master_Data[Transaction_ID]) -> 196
A6: Staples | B6: 27322.549 | D6: Grand Total | E6: 161291.92 | G6: CASH | H6: 40359.268 | J6: Tea 250g | K6: 12782.023 | M6: Units Sold | N6: =SUM(Master_Data[Qty]) -> 680
A7: Household | B7: 19525.543 | G7: Grand Total | H7: 161291.92 | J7: Butter 100g | K7: 12779.546 | M7: Average Basket Value | N7: =N4/N5 -> 822.91798 | P7: Average Basket Value | Q7: =IFERROR(GETPIVOTDATA("Net_Sales",$J$13)/GETPIVOTDATA("Transaction_ID",$L$13),0) -> 822.91798
A8: Snacks | B8: 18771.894 | J8: Curd 500g | K8: 10358.282
A9: Personal Care | B9: 18466.173 | J9: Grand Total | K9: 64962.026
A10: Grand Total | B10: 161291.92
J13: Total Sales | L13: Count of Transaction_ID | N13: Sum of Qty
J14: 161291.92 | L14: 196 | N14: 680

Sheet Dashboard
F1: =GETPIVOTDATA("Transaction_ID",'Pivot Analyse'!$L$13) -> 196 | H1: =GETPIVOTDATA("Qty",'Pivot Analyse'!$N$13) -> 680 | J1: ='Pivot Analyse'!Q7 -> 822.91798
D2: =GETPIVOTDATA("Net_Sales",'Pivot Analyse'!$J$13) -> 161291.92

Sheet Sales_Raw
A1: Transaction_ID | B1: Clean_Sale_Date | C1: Sale_Date | D1: Customer_ID | E1: Clean_Product_ID | F1: Product_ID | G1: Qty | H1: Unit_Price | I1: Discount Percentage | J1: Clean_Payment_Mode | K1: Payment_Mode | L1: Clean_Branch | M1: Branch | N1: Cashier | O1: Entered_Category | P1: Product_Name | Q1: Category | R1: Brand | S1: Cost_Price | T1: MRP | U1: Supplier | V1: Customer_Name | W1: Gender | X1: Age | Y1: City | Z1: Membership | AA1: Join_Date | AB1: Gross_ Sales | AC1: Net_Sales | AD1: Profit
A2: T0001 | B2: =DATEVALUE(Master_Data[[#This Row],[Sale_Date]]) -> 46266 | C2: 01-Sep-2026 | D2: C041 | E2: =UPPER(TRIM(Sales_Raw!$F2)) -> P1008 | F2: P1008 | G2: 3 | H2: 460.71 | I2: 0.15 | J2: =UPPER(TRIM(Sales_Raw!$K2)) -> CASH | K2: Cash | L2: =PROPER(TRIM(Sales_Raw!$M2)) -> Fairlands | M2: Fairlands | N2: Charan | O2: Dairy | P2: =VLOOKUP(Sales_Raw!$E2,ProductsMasterTable[#All],2,FALSE) -> Curd 500g | Q2: =VLOOKUP(Sales_Raw!$E2,ProductsMasterTable[#All],3,FALSE) -> Dairy | R2: =VLOOKUP(Sales_Raw!$E2,ProductsMasterTable[#All],4,FALSE) -> Aavin | S2: =VLOOKUP(Sales_Raw!$E2,ProductsMasterTable[#All],5,FALSE) -> 402.8 | T2: =VLOOKUP(Sales_Raw!$E2,ProductsMasterTable[#All],6,FALSE) -> 482.32 | U2: =VLOOKUP(Sales_Raw!$E2,ProductsMasterTable[#All],7,FALSE) -> FreshLine Traders | V2: =IFERROR(VLOOKUP(Sales_Raw!$D2,CustomersMasterTable[#All],2,FALSE),"Guest") -> Divya R | W2: =IFERROR(VLOOKUP(Sales_Raw!$D2,CustomersMasterTable[#All],3,FALSE),"Guest") -> Female | X2: =IFERROR(VLOOKUP(Sales_Raw!$D2,CustomersMasterTable[#All],4,FALSE),"Guest") -> 20 | Y2: =IFERROR(VLOOKUP(Sales_Raw!$D2,CustomersMasterTable[#All],5,FALSE),"Guest") -> Coimbatore | Z2: =IFERROR(VLOOKUP(Sales_Raw!$D2,CustomersMasterTable[#All],6,FALSE),"Guest") -> Regular | AA2: =IFERROR(VLOOKUP(Sales_Raw!$D2,CustomersMasterTable[#All],7,FALSE),"Guest") -> 46129 | AB2: =Master_Data[[#This Row],[Qty]]*Master_Data[[#This Row],[Unit_Price]] -> 1382.13 | AC2: =Master_Data[[#This Row],[Gross_ Sales]]*(1-Master_Data[[#This Row],[Discount Percentage]]) -> 1174.8105 | AD2: =Master_Data[[#This Row],[Net_Sales]]-(Master_Data[[#This Row],[Qty]]*Master_Data[[#This Row],[Cost_Price]]) -> -33.5895
A3: T0002 | B3: =DATEVALUE(Master_Data[[#This Row],[Sale_Date]]) -> 46256 | C3: 22-Aug-2026 | D3: C021 | E3: =UPPER(TRIM(Sales_Raw!$F3)) -> P1029 | F3: P1029 | G3: 5 | H3: 137.59 | I3: 0 | J3: =UPPER(TRIM(Sales_Raw!$K3)) -> UPI | K3: UPI | L3: =PROPER(TRIM(Sales_Raw!$M3)) -> Hasthampatti | M3: Hasthampatti | N3: Bala | O3: Household | P3: =VLOOKUP(Sales_Raw!$E3,ProductsMasterTable[#All],2,FALSE) -> Tissue Roll | Q3: =VLOOKUP(Sales_Raw!$E3,ProductsMasterTable[#All],3,FALSE) -> Household | R3: =VLOOKUP(Sales_Raw!$E3,ProductsMasterTable[#All],4,FALSE) -> Aachi | S3: =VLOOKUP(Sales_Raw!$E3,ProductsMasterTable[#All],5,FALSE) -> 119.07 | T3: =VLOOKUP(Sales_Raw!$E3,ProductsMasterTable[#All],6,FALSE) -> 148.51 | U3: =VLOOKUP(Sales_Raw!$E3,ProductsMasterTable[#All],7,FALSE) -> Salem Wholesale Mart | V3: =IFERROR(VLOOKUP(Sales_Raw!$D3,CustomersMasterTable[#All],2,FALSE),"Guest") -> Gayathri Kumar | W3: =IFERROR(VLOOKUP(Sales_Raw!$D3,CustomersMasterTable[#All],3,FALSE),"Guest") -> Female | X3: =IFERROR(VLOOKUP(Sales_Raw!$D3,CustomersMasterTable[#All],4,FALSE),"Guest") -> 21 | Y3: =IFERROR(VLOOKUP(Sales_Raw!$D3,CustomersMasterTable[#All],5,FALSE),"Guest") -> Salem | Z3: =IFERROR(VLOOKUP(Sales_Raw!$D3,CustomersMasterTable[#All],6,FALSE),"Guest") -> Silver | AA3: =IFERROR(VLOOKUP(Sales_Raw!$D3,CustomersMasterTable[#All],7,FALSE),"Guest") -> 46172 | AB3: =Master_Data[[#This Row],[Qty]]*Master_Data[[#This Row],[Unit_Price]] -> 687.95 | AC3: =Master_Data[[#This Row],[Gross_ Sales]]*(1-Master_Data[[#This Row],[Discount Percentage]]) -> 687.95 | AD3: =Master_Data[[#This Row],[Net_Sales]]-(Master_Data[[#This Row],[Qty]]*Master_Data[[#This Row],[Cost_Price]]) -> 92.6
A4: T0003 | B4: =DATEVALUE(Master_Data[[#This Row],[Sale_Date]]) -> 46248 | C4: 14-Aug-2026 | D4: C005 | E4: =UPPER(TRIM(Sales_Raw!$F4)) -> P1014 | F4: P1014 | G4: 4 | H4: 516.02 | I4: 0.05 | J4: =UPPER(TRIM(Sales_Raw!$K4)) -> CASH | K4: Cash | L4: =PROPER(TRIM(Sales_Raw!$M4)) -> Fairlands | M4: Fairlands | N4: Bala | O4: Snacks | P4: =VLOOKUP(Sales_Raw!$E4,ProductsMasterTable[#All],2,FALSE) -> Mixture 250g | Q4: =VLOOKUP(Sales_Raw!$E4,ProductsMasterTable[#All],3,FALSE) -> Snacks | R4: =VLOOKUP(Sales_Raw!$E4,ProductsMasterTable[#All],4,FALSE) -> Aavin | S4: =VLOOKUP(Sales_Raw!$E4,ProductsMasterTable[#All],5,FALSE) -> 414.06 | T4: =VLOOKUP(Sales_Raw!$E4,ProductsMasterTable[#All],6,FALSE) -> 545.2 | U4: =VLOOKUP(Sales_Raw!$E4,ProductsMasterTable[#All],7,FALSE) -> FreshLine Traders | V4: =IFERROR(VLOOKUP(Sales_Raw!$D4,CustomersMasterTable[#All],2,FALSE),"Guest") -> Anitha M | W4: =IFERROR(VLOOKUP(Sales_Raw!$D4,CustomersMasterTable[#All],3,FALSE),"Guest") -> Male | X4: =IFERROR(VLOOKUP(Sales_Raw!$D4,CustomersMasterTable[#All],4,FALSE),"Guest") -> 33 | Y4: =IFERROR(VLOOKUP(Sales_Raw!$D4,CustomersMasterTable[#All],5,FALSE),"Guest") -> Dharmapuri | Z4: =IFERROR(VLOOKUP(Sales_Raw!$D4,CustomersMasterTable[#All],6,FALSE),"Guest") -> Gold | AA4: =IFERROR(VLOOKUP(Sales_Raw!$D4,CustomersMasterTable[#All],7,FALSE),"Guest") -> 45745 | AB4: =Master_Data[[#This Row],[Qty]]*Master_Data[[#This Row],[Unit_Price]] -> 2064.08 | AC4: =Master_Data[[#This Row],[Gross_ Sales]]*(1-Master_Data[[#This Row],[Discount Percentage]]) -> 1960.876 | AD4: =Master_Data[[#This Row],[Net_Sales]]-(Master_Data[[#This Row],[Qty]]*Master_Data[[#This Row],[Cost_Price]]) -> 304.636
A5: T0004 | B5: =DATEVALUE(Master_Data[[#This Row],[Sale_Date]]) -> 46261 | C5: 27-Aug-2026 | D5: C025 | E5: =UPPER(TRIM(Sales_Raw!$F5)) -> P1029 | F5: P1029 | G5: 5 | H5: 147.87 | I5: 0 | J5: =UPPER(TRIM(Sales_Raw!$K5)) -> CARD | K5: Card | L5: =PROPER(TRIM(Sales_Raw!$M5)) -> Hasthampatti | M5: Hasthampatti | N5: Divya | O5: Household | P5: =VLOOKUP(Sales_Raw!$E5,ProductsMasterTable[#All],2,FALSE) -> Tissue Roll | Q5: =VLOOKUP(Sales_Raw!$E5,ProductsMasterTable[#All],3,FALSE) -> Household | R5: =VLOOKUP(Sales_Raw!$E5,ProductsMasterTable[#All],4,FALSE) -> Aachi | S5: =VLOOKUP(Sales_Raw!$E5,ProductsMasterTable[#All],5,FALSE) -> 119.07 | T5: =VLOOKUP(Sales_Raw!$E5,ProductsMasterTable[#All],6,FALSE) -> 148.51 | U5: =VLOOKUP(Sales_Raw!$E5,ProductsMasterTable[#All],7,FALSE) -> Salem Wholesale Mart | V5: =IFERROR(VLOOKUP(Sales_Raw!$D5,CustomersMasterTable[#All],2,FALSE),"Guest") -> Surya Priyan | W5: =IFERROR(VLOOKUP(Sales_Raw!$D5,CustomersMasterTable[#All],3,FALSE),"Guest") -> Female | X5: =IFERROR(VLOOKUP(Sales_Raw!$D5,CustomersMasterTable[#All],4,FALSE),"Guest") -> 34 | Y5: =IFERROR(VLOOKUP(Sales_Raw!$D5,CustomersMasterTable[#All],5,FALSE),"Guest") -> Erode | Z5: =IFERROR(VLOOKUP(Sales_Raw!$D5,CustomersMasterTable[#All],6,FALSE),"Guest") -> Silver | AA5: =IFERROR(VLOOKUP(Sales_Raw!$D5,CustomersMasterTable[#All],7,FALSE),"Guest") -> 45979 | AB5: =Master_Data[[#This Row],[Qty]]*Master_Data[[#This Row],[Unit_Price]] -> 739.35 | AC5: =Master_Data[[#This Row],[Gross_ Sales]]*(1-Master_Data[[#This Row],[Discount Percentage]]) -> 739.35 | AD5: =Master_Data[[#This Row],[Net_Sales]]-(Master_Data[[#This Row],[Qty]]*Master_Data[[#This Row],[Cost_Price]]) -> 144
A6: T0005 | B6: =DATEVALUE(Master_Data[[#This Row],[Sale_Date]]) -> 46235 | C6: 01-Aug-2026 | D6: C023 | E6: =UPPER(TRIM(Sales_Raw!$F6)) -> P1010 | F6: P1010 | G6: 4 | H6: 435.88 | I6: 0.05 | J6: =UPPER(TRIM(Sales_Raw!$K6)) -> CARD | K6: Card | L6: =PROPER(TRIM(Sales_Raw!$M6)) -> Suramangalam | M6: Suramangalam | N6: Ezhil | O6: Dairy | P6: =VLOOKUP(Sales_Raw!$E6,ProductsMasterTable[#All],2,FALSE) -> Butter 100g | Q6: =VLOOKUP(Sales_Raw!$E6,ProductsMasterTable[#All],3,FALSE) -> Dairy | R6: =VLOOKUP(Sales_Raw!$E6,ProductsMasterTable[#All],4,FALSE) -> Cavin's | S6: =VLOOKUP(Sales_Raw!$E6,ProductsMasterTable[#All],5,FALSE) -> 342.47 | T6: =VLOOKUP(Sales_Raw!$E6,ProductsMasterTable[#All],6,FALSE) -> 441.05 | U6: =VLOOKUP(Sales_Raw!$E6,ProductsMasterTable[#All],7,FALSE) -> Salem Wholesale Mart | V6: =IFERROR(VLOOKUP(Sales_Raw!$D6,CustomersMasterTable[#All],2,FALSE),"Guest") -> Janani R | W6: =IFERROR(VLOOKUP(Sales_Raw!$D6,CustomersMasterTable[#All],3,FALSE),"Guest") -> Male | X6: =IFERROR(VLOOKUP(Sales_Raw!$D6,CustomersMasterTable[#All],4,FALSE),"Guest") -> 43 | Y6: =IFERROR(VLOOKUP(Sales_Raw!$D6,CustomersMasterTable[#All],5,FALSE),"Guest") -> Salem | Z6: =IFERROR(VLOOKUP(Sales_Raw!$D6,CustomersMasterTable[#All],6,FALSE),"Guest") -> Gold | AA6: =IFERROR(VLOOKUP(Sales_Raw!$D6,CustomersMasterTable[#All],7,FALSE),"Guest") -> 46241 | AB6: =Master_Data[[#This Row],[Qty]]*Master_Data[[#This Row],[Unit_Price]] -> 1743.52 | AC6: =Master_Data[[#This Row],[Gross_ Sales]]*(1-Master_Data[[#This Row],[Discount Percentage]]) -> 1656.344 | AD6: =Master_Data[[#This Row],[Net_Sales]]-(Master_Data[[#This Row],[Qty]]*Master_Data[[#This Row],[Cost_Price]]) -> 286.464
A7: T0006 | B7: =DATEVALUE(Master_Data[[#This Row],[Sale_Date]]) -> 46249 | C7: 15-Aug-2026 | D7: C032 | E7: =UPPER(TRIM(Sales_Raw!$F7)) -> P1008 | F7: P1008 | G7: 3 | H7: 460.55 | I7: 0 | J7: =UPPER(TRIM(Sales_Raw!$K7)) -> CASH | K7: Cash | L7: =PROPER(TRIM(Sales_Raw!$M7)) -> Hasthampatti | M7: Hasthampatti | N7: Divya | O7: Dairy | P7: =VLOOKUP(Sales_Raw!$E7,ProductsMasterTable[#All],2,FALSE) -> Curd 500g | Q7: =VLOOKUP(Sales_Raw!$E7,ProductsMasterTable[#All],3,FALSE) -> Dairy | R7: =VLOOKUP(Sales_Raw!$E7,ProductsMasterTable[#All],4,FALSE) -> Aavin | S7: =VLOOKUP(Sales_Raw!$E7,ProductsMasterTable[#All],5,FALSE) -> 402.8 | T7: =VLOOKUP(Sales_Raw!$E7,ProductsMasterTable[#All],6,FALSE) -> 482.32 | U7: =VLOOKUP(Sales_Raw!$E7,ProductsMasterTable[#All],7,FALSE) -> FreshLine Traders | V7: =IFERROR(VLOOKUP(Sales_Raw!$D7,CustomersMasterTable[#All],2,FALSE),"Guest") -> Anitha Shree | W7: =IFERROR(VLOOKUP(Sales_Raw!$D7,CustomersMasterTable[#All],3,FALSE),"Guest") -> Male | X7: =IFERROR(VLOOKUP(Sales_Raw!$D7,CustomersMasterTable[#All],4,FALSE),"Guest") -> 63 | Y7: =IFERROR(VLOOKUP(Sales_Raw!$D7,CustomersMasterTable[#All],5,FALSE),"Guest") -> Namakkal | Z7: =IFERROR(VLOOKUP(Sales_Raw!$D7,CustomersMasterTable[#All],6,FALSE),"Guest") -> Regular | AA7: =IFERROR(VLOOKUP(Sales_Raw!$D7,CustomersMasterTable[#All],7,FALSE),"Guest") -> 45928 | AB7: =Master_Data[[#This Row],[Qty]]*Master_Data[[#This Row],[Unit_Price]] -> 1381.65 | AC7: =Master_Data[[#This Row],[Gross_ Sales]]*(1-Master_Data[[#This Row],[Discount Percentage]]) -> 1381.65 | AD7: =Master_Data[[#This Row],[Net_Sales]]-(Master_Data[[#This Row],[Qty]]*Master_Data[[#This Row],[Cost_Price]]) -> 173.25
A8: T0007 | B8: =DATEVALUE(Master_Data[[#This Row],[Sale_Date]]) -> 46245 | C8: 11/08/2026 | D8: C054 | E8: =UPPER(TRIM(Sales_Raw!$F8)) -> P1015 | F8: P1015 | G8: 2 | H8: 164.04 | I8: 0.1 | J8: =UPPER(TRIM(Sales_Raw!$K8)) -> UPI | K8: UPI | L8: =PROPER(TRIM(Sales_Raw!$M8)) -> Hasthampatti | M8: Hasthampatti | N8: Ezhil | O8: Snacks | P8: =VLOOKUP(Sales_Raw!$E8,ProductsMasterTable[#All],2,FALSE) -> Biscuits Pack | Q8: =VLOOKUP(Sales_Raw!$E8,ProductsMasterTable[#All],3,FALSE) -> Snacks | R8: =VLOOKUP(Sales_Raw!$E8,ProductsMasterTable[#All],4,FALSE) -> HUL | S8: =VLOOKUP(Sales_Raw!$E8,ProductsMasterTable[#All],5,FALSE) -> 129.75 | T8: =VLOOKUP(Sales_Raw!$E8,ProductsMasterTable[#All],6,FALSE) -> 164.29 | U8: =VLOOKUP(Sales_Raw!$E8,ProductsMasterTable[#All],7,FALSE) -> Kongu Distributors | V8: =IFERROR(VLOOKUP(Sales_Raw!$D8,CustomersMasterTable[#All],2,FALSE),"Guest") -> Naveen S | W8: =IFERROR(VLOOKUP(Sales_Raw!$D8,CustomersMasterTable[#All],3,FALSE),"Guest") -> Male | X8: =IFERROR(VLOOKUP(Sales_Raw!$D8,CustomersMasterTable[#All],4,FALSE),"Guest") -> 20 | Y8: =IFERROR(VLOOKUP(Sales_Raw!$D8,CustomersMasterTable[#All],5,FALSE),"Guest") -> Erode | Z8: =IFERROR(VLOOKUP(Sales_Raw!$D8,CustomersMasterTable[#All],6,FALSE),"Guest") -> Gold | AA8: =IFERROR(VLOOKUP(Sales_Raw!$D8,CustomersMasterTable[#All],7,FALSE),"Guest") -> 45732 | AB8: =Master_Data[[#This Row],[Qty]]*Master_Data[[#This Row],[Unit_Price]] -> 328.08 | AC8: =Master_Data[[#This Row],[Gross_ Sales]]*(1-Master_Data[[#This Row],[Discount Percentage]]) -> 295.272 | AD8: =Master_Data[[#This Row],[Net_Sales]]-(Master_Data[[#This Row],[Qty]]*Master_Data[[#This Row],[Cost_Price]]) -> 35.772
A9: T0008 | B9: =DATEVALUE(Master_Data[[#This Row],[Sale_Date]]) -> 46271 | C9: 06-Sep-2026 | D9: C043 | E9: =UPPER(TRIM(Sales_Raw!$F9)) -> P1001 | F9: P1001 | G9: 1 | H9: 300.79 | I9: 0 | J9: =UPPER(TRIM(Sales_Raw!$K9)) -> CASH | K9: Cash | L9: =PROPER(TRIM(Sales_Raw!$M9)) -> Fairlands | M9: Fairlands | N9: Asha | O9: Staples | P9: =VLOOKUP(Sales_Raw!$E9,ProductsMasterTable[#All],2,FALSE) -> Rice 5kg | Q9: =VLOOKUP(Sales_Raw!$E9,ProductsMasterTable[#All],3,FALSE) -> Staples | R9: =VLOOKUP(Sales_Raw!$E9,ProductsMasterTable[#All],4,FALSE) -> Nestle | S9: =VLOOKUP(Sales_Raw!$E9,ProductsMasterTable[#All],5,FALSE) -> 275.05 | T9: =VLOOKUP(Sales_Raw!$E9,ProductsMasterTable[#All],6,FALSE) -> 309.64 | U9: =VLOOKUP(Sales_Raw!$E9,ProductsMasterTable[#All],7,FALSE) -> Kongu Distributors | V9: =IFERROR(VLOOKUP(Sales_Raw!$D9,CustomersMasterTable[#All],2,FALSE),"Guest") -> Harish Raj | W9: =IFERROR(VLOOKUP(Sales_Raw!$D9,CustomersMasterTable[#All],3,FALSE),"Guest") -> Male | X9: =IFERROR(VLOOKUP(Sales_Raw!$D9,CustomersMasterTable[#All],4,FALSE),"Guest") -> 67 | Y9: =IFERROR(VLOOKUP(Sales_Raw!$D9,CustomersMasterTable[#All],5,FALSE),"Guest") -> Namakkal | Z9: =IFERROR(VLOOKUP(Sales_Raw!$D9,CustomersMasterTable[#All],6,FALSE),"Guest") -> Regular | AA9: =IFERROR(VLOOKUP(Sales_Raw!$D9,CustomersMasterTable[#All],7,FALSE),"Guest") -> 46179 | AB9: =Master_Data[[#This Row],[Qty]]*Master_Data[[#This Row],[Unit_Price]] -> 300.79 | AC9: =Master_Data[[#This Row],[Gross_ Sales]]*(1-Master_Data[[#This Row],[Discount Percentage]]) -> 300.79 | AD9: =Master_Data[[#This Row],[Net_Sales]]-(Master_Data[[#This Row],[Qty]]*Master_Data[[#This Row],[Cost_Price]]) -> 25.74
A10: T0009 | B10: =DATEVALUE(Master_Data[[#This Row],[Sale_Date]]) -> 46251 | C10: 17-Aug-2026 | D10: C025 | E10: =UPPER(TRIM(Sales_Raw!$F10)) -> P1011 | F10: P1011 | G10: 2 | H10: 472.37 | I10: 0 | J10: =UPPER(TRIM(Sales_Raw!$K10)) -> CASH | K10: Cash | L10: =PROPER(TRIM(Sales_Raw!$M10)) -> Hasthampatti | M10: Hasthampatti | N10: Divya | O10: Dairy | P10: =VLOOKUP(Sales_Raw!$E10,ProductsMasterTable[#All],2,FALSE) -> Cheese Slices | Q10: =VLOOKUP(Sales_Raw!$E10,ProductsMasterTable[#All],3,FALSE) -> Dairy | R10: =VLOOKUP(Sales_Raw!$E10,ProductsMasterTable[#All],4,FALSE) -> Cavin's | S10: =VLOOKUP(Sales_Raw!$E10,ProductsMasterTable[#All],5,FALSE) -> 409.19 | T10: =VLOOKUP(Sales_Raw!$E10,ProductsMasterTable[#All],6,FALSE) -> 493.92 | U10: =VLOOKUP(Sales_Raw!$E10,ProductsMasterTable[#All],7,FALSE) -> Metro Supply Co | V10: =IFERROR(VLOOKUP(Sales_Raw!$D10,CustomersMasterTable[#All],2,FALSE),"Guest") -> Surya Priyan | W10: =IFERROR(VLOOKUP(Sales_Raw!$D10,CustomersMasterTable[#All],3,FALSE),"Guest") -> Female | X10: =IFERROR(VLOOKUP(Sales_Raw!$D10,CustomersMasterTable[#All],4,FALSE),"Guest") -> 34 | Y10: =IFERROR(VLOOKUP(Sales_Raw!$D10,CustomersMasterTable[#All],5,FALSE),"Guest") -> Erode | Z10: =IFERROR(VLOOKUP(Sales_Raw!$D10,CustomersMasterTable[#All],6,FALSE),"Guest") -> Silver | AA10: =IFERROR(VLOOKUP(Sales_Raw!$D10,CustomersMasterTable[#All],7,FALSE),"Guest") -> 45979 | AB10: =Master_Data[[#This Row],[Qty]]*Master_Data[[#This Row],[Unit_Price]] -> 944.74 | AC10: =Master_Data[[#This Row],[Gross_ Sales]]*(1-Master_Data[[#This Row],[Discount Percentage]]) -> 944.74 | AD10: =Master_Data[[#This Row],[Net_Sales]]-(Master_Data[[#This Row],[Qty]]*Master_Data[[#This Row],[Cost_Price]]) -> 126.36
A11: T0010 | B11: =DATEVALUE(Master_Data[[#This Row],[Sale_Date]]) -> 46251 | C11: 17-Aug-2026 | D11: C054 | E11: =UPPER(TRIM(Sales_Raw!$F11)) -> P1003 | F11: P1003 | G11: 4 | H11: 265.31 | I11: 0.1 | J11: =UPPER(TRIM(Sales_Raw!$K11)) -> UPI | K11: UPI | L11: =PROPER(TRIM(Sales_Raw!$M11)) -> Hasthampatti | M11: Hasthampatti | N11: Bala | O11: Staples | P11: =VLOOKUP(Sales_Raw!$E11,ProductsMasterTable[#All],2,FALSE) -> Toor Dal 1kg | Q11: =VLOOKUP(Sales_Raw!$E11,ProductsMasterTable[#All],3,FALSE) -> Staples | R11: =VLOOKUP(Sales_Raw!$E11,ProductsMasterTable[#All],4,FALSE) -> Aavin | S11: =VLOOKUP(Sales_Raw!$E11,ProductsMasterTable[#All],5,FALSE) -> 255.38 | T11: =VLOOKUP(Sales_Raw!$E11,ProductsMasterTable[#All],6,FALSE) -> 287.89 | U11: =VLOOKUP(Sales_Raw!$E11,ProductsMasterTable[#All],7,FALSE) -> Kongu Distributors | V11: =IFERROR(VLOOKUP(Sales_Raw!$D11,CustomersMasterTable[#All],2,FALSE),"Guest") -> Naveen S | W11: =IFERROR(VLOOKUP(Sales_Raw!$D11,CustomersMasterTable[#All],3,FALSE),"Guest") -> Male | X11: =IFERROR(VLOOKUP(Sales_Raw!$D11,CustomersMasterTable[#All],4,FALSE),"Guest") -> 20 | Y11: =IFERROR(VLOOKUP(Sales_Raw!$D11,CustomersMasterTable[#All],5,FALSE),"Guest") -> Erode | Z11: =IFERROR(VLOOKUP(Sales_Raw!$D11,CustomersMasterTable[#All],6,FALSE),"Guest") -> Gold | AA11: =IFERROR(VLOOKUP(Sales_Raw!$D11,CustomersMasterTable[#All],7,FALSE),"Guest") -> 45732 | AB11: =Master_Data[[#This Row],[Qty]]*Master_Data[[#This Row],[Unit_Price]] -> 1061.24 | AC11: =Master_Data[[#This Row],[Gross_ Sales]]*(1-Master_Data[[#This Row],[Discount Percentage]]) -> 955.116 | AD11: =Master_Data[[#This Row],[Net_Sales]]-(Master_Data[[#This Row],[Qty]]*Master_Data[[#This Row],[Cost_Price]]) -> -66.404
A12: T0011 | B12: =DATEVALUE(Master_Data[[#This Row],[Sale_Date]]) -> 46239 | C12: 05-Aug-2026 | D12: C050 | E12: =UPPER(TRIM(Sales_Raw!$F12)) -> P1021 | F12: P1021 | G12: 1 | H12: 58.16 | I12: 0 | J12: =UPPER(TRIM(Sales_Raw!$K12)) -> UPI | K12: upi | L12: =PROPER(TRIM(Sales_Raw!$M12)) -> Fairlands | M12: Fairlands | N12: Ezhil | O12: Beverages | P12: =VLOOKUP(Sales_Raw!$E12,ProductsMasterTable[#All],2,FALSE) -> Coffee 200g | Q12: =VLOOKUP(Sales_Raw!$E12,ProductsMasterTable[#All],3,FALSE) -> Beverages | R12: =VLOOKUP(Sales_Raw!$E12,ProductsMasterTable[#All],4,FALSE) -> Surf | S12: =VLOOKUP(Sales_Raw!$E12,ProductsMasterTable[#All],5,FALSE) -> 44.61 | T12: =VLOOKUP(Sales_Raw!$E12,ProductsMasterTable[#All],6,FALSE) -> 59.33 | U12: =VLOOKUP(Sales_Raw!$E12,ProductsMasterTable[#All],7,FALSE) -> Metro Supply Co | V12: =IFERROR(VLOOKUP(Sales_Raw!$D12,CustomersMasterTable[#All],2,FALSE),"Guest") -> Divya Shree | W12: =IFERROR(VLOOKUP(Sales_Raw!$D12,CustomersMasterTable[#All],3,FALSE),"Guest") -> Female | X12: =IFERROR(VLOOKUP(Sales_Raw!$D12,CustomersMasterTable[#All],4,FALSE),"Guest") -> 43 | Y12: =IFERROR(VLOOKUP(Sales_Raw!$D12,CustomersMasterTable[#All],5,FALSE),"Guest") -> Dharmapuri | Z12: =IFERROR(VLOOKUP(Sales_Raw!$D12,CustomersMasterTable[#All],6,FALSE),"Guest") -> Silver | AA12: =IFERROR(VLOOKUP(Sales_Raw!$D12,CustomersMasterTable[#All],7,FALSE),"Guest") -> 45969 | AB12: =Master_Data[[#This Row],[Qty]]*Master_Data[[#This Row],[Unit_Price]] -> 58.16 | AC12: =Master_Data[[#This Row],[Gross_ Sales]]*(1-Master_Data[[#This Row],[Discount Percentage]]) -> 58.16 | AD12: =Master_Data[[#This Row],[Net_Sales]]-(Master_Data[[#This Row],[Qty]]*Master_Data[[#This Row],[Cost_Price]]) -> 13.55
A13: T0012 | B13: =DATEVALUE(Master_Data[[#This Row],[Sale_Date]]) -> 46244 | C13: 10-Aug-2026 | D13: C016 | E13: =UPPER(TRIM(Sales_Raw!$F13)) -> P1005 | F13: P1005 | G13: 4 | H13: 381.51 | I13: 0.1 | J13: =UPPER(TRIM(Sales_Raw!$K13)) -> UPI | K13: UPI | L13: =PROPER(TRIM(Sales_Raw!$M13)) -> Hasthampatti | M13: Hasthampatti | N13: Charan | O13: Staples | P13: =VLOOKUP(Sales_Raw!$E13,ProductsMasterTable[#All],2,FALSE) -> Sugar 1kg | Q13: =VLOOKUP(Sales_Raw!$E13,ProductsMasterTable[#All],3,FALSE) -> Staples | R13: =VLOOKUP(Sales_Raw!$E13,ProductsMasterTable[#All],4,FALSE) -> ITC | S13: =VLOOKUP(Sales_Raw!$E13,ProductsMasterTable[#All],5,FALSE) -> 305.84 | T13: =VLOOKUP(Sales_Raw!$E13,ProductsMasterTable[#All],6,FALSE) -> 391.87 | U13: =VLOOKUP(Sales_Raw!$E13,ProductsMasterTable[#All],7,FALSE) -> Kongu Distributors | V13: =IFERROR(VLOOKUP(Sales_Raw!$D13,CustomersMasterTable[#All],2,FALSE),"Guest") -> Sanjay Babu | W13: =IFERROR(VLOOKUP(Sales_Raw!$D13,CustomersMasterTable[#All],3,FALSE),"Guest") -> Male | X13: =IFERROR(VLOOKUP(Sales_Raw!$D13,CustomersMasterTable[#All],4,FALSE),"Guest") -> 22 | Y13: =IFERROR(VLOOKUP(Sales_Raw!$D13,CustomersMasterTable[#All],5,FALSE),"Guest") -> Coimbatore | Z13: =IFERROR(VLOOKUP(Sales_Raw!$D13,CustomersMasterTable[#All],6,FALSE),"Guest") -> Silver | AA13: =IFERROR(VLOOKUP(Sales_Raw!$D13,CustomersMasterTable[#All],7,FALSE),"Guest") -> 46221 | AB13: =Master_Data[[#This Row],[Qty]]*Master_Data[[#This Row],[Unit_Price]] -> 1526.04 | AC13: =Master_Data[[#This Row],[Gross_ Sales]]*(1-Master_Data[[#This Row],[Discount Percentage]]) -> 1373.436 | AD13: =Master_Data[[#This Row],[Net_Sales]]-(Master_Data[[#This Row],[Qty]]*Master_Data[[#This Row],[Cost_Price]]) -> 150.076
... A197: T0196 | B197: =DATEVALUE(Master_Data[[#This Row],[Sale_Date]]) -> 46255 | C197: 21-Aug-2026 | D197: C011 | E197: =UPPER(TRIM(Sales_Raw!$F197)) -> P1013 | F197: p1013 | G197: 5 | H197: 106 | I197: 0 | J197: =UPPER(TRIM(Sales_Raw!$K197)) -> CARD | K197: Card | L197: =PROPER(TRIM(Sales_Raw!$M197)) -> Hasthampatti | M197: Hasthampatti | N197: Ezhil | O197: Snacks | P197: =VLOOKUP(Sales_Raw!$E197,ProductsMasterTable[#All],2,FALSE) -> Banana Chips | Q197: =VLOOKUP(Sales_Raw!$E197,ProductsMasterTable[#All],3,FALSE) -> Snacks | R197: =VLOOKUP(Sales_Raw!$E197,ProductsMasterTable[#All],4,FALSE) -> Tata | S197: =VLOOKUP(Sales_Raw!$E197,ProductsMasterTable[#All],5,FALSE) -> 95.3 | T197: =VLOOKUP(Sales_Raw!$E197,ProductsMasterTable[#All],6,FALSE) -> 108.26 | U197: =VLOOKUP(Sales_Raw!$E197,ProductsMasterTable[#All],7,FALSE) -> Metro Supply Co | V197: =IFERROR(VLOOKUP(Sales_Raw!$D197,CustomersMasterTable[#All],2,FALSE),"Guest") -> Meena Priyan | W197: =IFERROR(VLOOKUP(Sales_Raw!$D197,CustomersMasterTable[#All],3,FALSE),"Guest") -> Male | X197: =IFERROR(VLOOKUP(Sales_Raw!$D197,CustomersMasterTable[#All],4,FALSE),"Guest") -> 35 | Y197: =IFERROR(VLOOKUP(Sales_Raw!$D197,CustomersMasterTable[#All],5,FALSE),"Guest") -> Karur | Z197: =IFERROR(VLOOKUP(Sales_Raw!$D197,CustomersMasterTable[#All],6,FALSE),"Guest") -> Regular | AA197: =IFERROR(VLOOKUP(Sales_Raw!$D197,CustomersMasterTable[#All],7,FALSE),"Guest") -> 46210 | AB197: =Master_Data[[#This Row],[Qty]]*Master_Data[[#This Row],[Unit_Price]] -> 530 | AC197: =Master_Data[[#This Row],[Gross_ Sales]]*(1-Master_Data[[#This Row],[Discount Percentage]]) -> 530 | AD197: =Master_Data[[#This Row],[Net_Sales]]-(Master_Data[[#This Row],[Qty]]*Master_Data[[#This Row],[Cost_Price]]) -> 53.5

Sheet Products_Master
A1: Product_ID | B1: Product_Name | C1: Category | D1: Brand | E1: Cost_Price | F1: MRP | G1: Supplier
A2: P1001 | B2: Rice 5kg | C2: Staples | D2: Nestle | E2: 275.05 | F2: 309.64 | G2: Kongu Distributors
A3: P1002 | B3: Wheat Flour 5kg | C3: Staples | D3: Cavin's | E3: 107.73 | F3: 138.91 | G3: Salem Wholesale Mart
A4: P1003 | B4: Toor Dal 1kg | C4: Staples | D4: Aavin | E4: 255.38 | F4: 287.89 | G4: Kongu Distributors
A5: P1004 | B5: Urad Dal 1kg | C5: Staples | D5: Cavin's | E5: 111.53 | F5: 140.36 | G5: Kongu Distributors
A6: P1005 | B6: Sugar 1kg | C6: Staples | D6: ITC | E6: 305.84 | F6: 391.87 | G6: Kongu Distributors
A7: P1006 | B7: Salt 1kg | C7: Staples | D7: Aachi | E7: 198.58 | F7: 235.12 | G7: Kongu Distributors
A8: P1007 | B8: Milk 1L | C8: Dairy | D8: Britannia | E8: 298.65 | F8: 357.86 | G8: Kongu Distributors
A9: P1008 | B9: Curd 500g | C9: Dairy | D9: Aavin | E9: 402.8 | F9: 482.32 | G9: FreshLine Traders
A10: P1009 | B10: Paneer 200g | C10: Dairy | D10: Surf | E10: 56.88 | F10: 74.79 | G10: Metro Supply Co
A11: P1010 | B11: Butter 100g | C11: Dairy | D11: Cavin's | E11: 342.47 | F11: 441.05 | G11: Salem Wholesale Mart
A12: P1011 | B12: Cheese Slices | C12: Dairy | D12: Cavin's | E12: 409.19 | F12: 493.92 | G12: Metro Supply Co
A13: P1012 | B13: Potato Chips | C13: Snacks | D13: HUL | E13: 351.42 | F13: 443.58 | G13: Sri Ganesh Agencies
... A31: P1030 | B31: Garbage Bags | C31: Household | D31: Nestle | E31: 292.05 | F31: 363.17 | G31: Metro Supply Co

Sheet Customers_Master
A1: Customer_ID | B1: Customer_Name | C1: Gender | D1: Age | E1: City | F1: Membership | G1: Join_Date
A2: C001 | B2: Priya Raj | C2: Female | D2: 28 | E2: Coimbatore | F2: Regular | G2: 45927
A3: C002 | B3: Praveen S | C3: Male | D3: 58 | E3: Namakkal | F3: Silver | G3: 46177
A4: C003 | B4: Janani M | C4: Male | D4: 41 | E4: Erode | F4: Regular | G4: 46201
A5: C004 | B5: Arun Shree | C5: Female | D5: 49 | E5: Salem | F5: Regular | G5: 46029
A6: C005 | B6: Anitha M | C6: Male | D6: 33 | E6: Dharmapuri | F6: Gold | G6: 45745
A7: C006 | B7: Nithya R | C7: Male | D7: 26 | E7: Karur | F7: Regular | G7: 46220
A8: C007 | B8: Divya Raj | C8: Female | D8: 31 | E8: Dharmapuri | F8: Silver | G8: 45863
A9: C008 | B9: Anitha Selvam | C9: Female | D9: 46 | E9: Dharmapuri | F9: Regular | G9: 45911
A10: C009 | B10: Keerthi R | C10: Female | D10: 19 | E10: Dharmapuri | F10: Silver | G10: 45883
A11: C010 | B11: Arun R | C11: Male | D11: 32 | E11: Salem | F11: Gold | G11: 45996
A12: C011 | B12: Meena Priyan | C12: Male | D12: 35 | E12: Karur | F12: Regular | G12: 46210
A13: C012 | B13: Vignesh Shree | C13: Female | D13: 33 | E13: Coimbatore | F13: Silver | G13: 45852
... A61: C060 | B61: Karthik Raj | C61: Male | D61: 58 | E61: Namakkal | F61: Silver | G61: 46191

Sheet Insights
B1: Turn Charts into Insights
B2: The highest-selling category is ______.
B3: The strongest product is ______ and the weakest among the top set is ______.
B4: The ______ branch performs best, and most sales are paid through ______.
